guide.py
split_library.py
split_library-0.0.6.dist-info/METADATA
split_library-0.0.6.dist-info/WHEEL
split_library-0.0.6.dist-info/top_level.txt
split_library-0.0.6.dist-info/RECORD
