Metadata-Version: 2.1
Name: split-library
Version: 0.0.6
Summary: Split library for VRP developed by Jamie
Home-page: UNKNOWN
Author: Jamie Nguyen
Author-email: thangnmtfac@gmail.com
License: UNKNOWN
Platform: UNKNOWN
Requires-Dist: numba (~=0.55.1)
